skretry/__init__.py
skretry/api.py
skretry/compat.py
skretry-0.1.6.dist-info/LICENSE
skretry-0.1.6.dist-info/METADATA
skretry-0.1.6.dist-info/WHEEL
skretry-0.1.6.dist-info/top_level.txt
skretry-0.1.6.dist-info/RECORD
